__init__.py
diffeal/__init__.py
diffeal/models.py
diffeal/toolbox.py
diffeo_elasticity-0.1.3.dist-info/licenses/LICENSE
diffeo_elasticity-0.1.3.dist-info/METADATA
diffeo_elasticity-0.1.3.dist-info/WHEEL
diffeo_elasticity-0.1.3.dist-info/top_level.txt
diffeo_elasticity-0.1.3.dist-info/RECORD
